{
	"monsters": [
		{
			"id": "aknosom",
			"name": "Aknosom"
		},
		{
			"id": "almudron",
			"name": "Almudron"
		},
		{
			"id": "almudron_magma",
			"name": "Almudron Magma"
		},
		{
			"id": "anjanath",
			"name": "Anjanath"
		},
		{
			"id": "arzuros",
			"name": "Arzuros"
		},
		{
			"id": "arzuros_apex",
			"name": "Arzuros Apex"
		},
		{
			"id": "astalos",
			"name": "Astalos"
		},
		{
			"id": "barioth",
			"name": "Barioth"
		},
		{
			"id": "barroth",
			"name": "Barroth"
		},
		{
			"id": "basarios",
			"name": "Basarios"
		},
		{
			"id": "bazelgeuse",
			"name": "Bazelgeuse"
		},
		{
			"id": "bazelgeuse_seething",
			"name": "Bazelgeuse Magma"
		},
		{
			"id": "bishaten",
			"name": "Bishaten"
		},
		{
			"id": "bishaten_blood_orange",
			"name": "Bishaten Sanguina"
		},
		{
			"id": "chameleos",
			"name": "Chameleos"
		},
		{
			"id": "chameleos_risen",
			"name": "Chameleos elevado"
		},
		{
			"id": "daimyo_hermitaur",
			"name": "Daimyo Hermitaur"
		},
		{
			"id": "diablos",
			"name": "Diablos"
		},
		{
			"id": "espinas",
			"name": "Espinas"
		},
		{
			"id": "espinas_flaming",
			"name": "Espinas Llameante"
		},
		{
			"id": "garangolm",
			"name": "Garangolm"
		},
		{
			"id": "gore_magala",
			"name": "Gore Magala"
		},
		{
			"id": "gore_magala_chaotic",
			"name": "Gore Magala caótico"
		},
		{
			"id": "goss_harag",
			"name": "Goss Harag"
		},
		{
			"id": "great_baggi",
			"name": "Gran Baggi"
		},
		{
			"id": "great_izuchi",
			"name": "Gran Izuchi"
		},
		{
			"id": "great_wroggi",
			"name": "Gran Wroggi"
		},
		{
			"id": "jyuratodus",
			"name": "Jyuratodus"
		},
		{
			"id": "khezu",
			"name": "Khezu"
		},
		{
			"id": "kulu_ya_ku",
			"name": "Kulu-Ya-Ku"
		},
		{
			"id": "kushala_daora",
			"name": "Kushala Daora"
		},
		{
			"id": "kushala_daora_risen",
			"name": "Kushala Daora elevado"
		},
		{
			"id": "lagombi",
			"name": "Lagombi"
		},
		{
			"id": "lunagaron",
			"name": "Lunagaron"
		},
		{
			"id": "magnamalo",
			"name": "Magnamalo"
		},
		{
			"id": "magnamalo_scorned",
			"name": "Magnamalo humillado"
		},
		{
			"id": "malzeno",
			"name": "Malzeno"
		},
		{
			"id": "malzeno_primordial",
			"name": "Malzeno primordial"
		},
		{
			"id": "mizutsune",
			"name": "Mizutsune"
		},
		{
			"id": "mizutsune_violet",
			"name": "Mizutsune Violeta"
		},
		{
			"id": "mizutsune_apex",
			"name": "Mizutsune Apex"
		},
		{
			"id": "nargacuga",
			"name": "Nargacuga"
		},
		{
			"id": "nargacuga_lucent",
			"name": "Nargacuga Lunar"
		},
		{
			"id": "pukei_pukei",
			"name": "Pukei-Pukei"
		},
		{
			"id": "rajang",
			"name": "Rajang"
		},
		{
			"id": "rajang_furious",
			"name": "Rajang Rabioso"
		},
		{
			"id": "rakna_kadaki",
			"name": "Rakna-Kadaki"
		},
		{
			"id": "rakna_kadaki_pyre",
			"name": "Rakna-Kadaki Pira"
		},
		{
			"id": "rathalos",
			"name": "Rathalos"
		},
		{
			"id": "rathalos_silver",
			"name": "Rathalos Plateado"
		},
		{
			"id": "rathian",
			"name": "Rathian"
		},
		{
			"id": "rathian_gold",
			"name": "Rathian Dorada"
		},
		{
			"id": "rathian_apex",
			"name": "Rathian Apex"
		},
		{
			"id": "royal_ludroth",
			"name": "Ludroth Real"
		},
		{
			"id": "seregios",
			"name": "Seregios"
		},
		{
			"id": "shagaru_magala",
			"name": "Shagaru Magala"
		},
		{
			"id": "shagaru_magala_risen",
			"name": "Shagaru Magala elevado"
		},
		{
			"id": "shogun_ceanataur",
			"name": "Shogun Ceanataur"
		},
		{
			"id": "somnacanth",
			"name": "Somnacanth"
		},
		{
			"id": "somnacanth_aurora",
			"name": "Somnacanth Aurora"
		},
		{
			"id": "teostra",
			"name": "Teostra"
		},
		{
			"id": "teostra_risen",
			"name": "Teostra elevado"
		},
		{
			"id": "tetranadon",
			"name": "Tetranadon"
		},
		{
			"id": "tigrex",
			"name": "Tigrex"
		},
		{
			"id": "tobi_kadachi",
			"name": "Tobi-Kadachi"
		},
		{
			"id": "velkhana",
			"name": "Velkhana"
		},
		{
			"id": "volvidon",
			"name": "Volvidon"
		},
		{
			"id": "zinogre",
			"name": "Zinogre"
		}
	]
}
