{
	"id": "astalos",
	"version": "16.0.0",
	"type": "flying_wyvern",
	"physiologies": [
		{
			"parts": [
				"crest"
			],
			"values": [
				{
					"states": [
						"default"
					],
					"slash": 55,
					"impact": 55,
					"shot": 30,
					"fire": 5,
					"water": 5,
					"thunder": 0,
					"ice": 10,
					"dragon": 5,
					"stun": 100
				},
				{
					"states": [
						"broken"
					],
					"slash": 57,
					"impact": 57,
					"shot": 30,
					"fire": 5,
					"water": 5,
					"thunder": 0,
					"ice": 10,
					"dragon": 5,
					"stun": 100
				},
				{
					"states": [
						"charged_electric"
					],
					"slash": 63,
					"impact": 63,
					"shot": 50,
					"fire": 5,
					"water": 15,
					"thunder": 0,
					"ice": 15,
					"dragon": 5,
					"stun": 100
				}
			]
		},
		{
			"parts": [
				"abdomen"
			],
			"values": [
				{
					"states": [
						"default"
					],
					"slash": 24,
					"impact": 24,
					"shot": 15,
					"fire": 5,
					"water": 5,
					"thunder": 0,
					"ice": 10,
					"dragon": 5,
					"stun": 0
				}
			]
		},
		{
			"parts": [
				"neck"
			],
			"values": [
				{
					"states": [
						"default"
					],
					"slash": 55,
					"impact": 55,
					"shot": 30,
					"fire": 5,
					"water": 5,
					"thunder": 0,
					"ice": 5,
					"dragon": 5,
					"stun": 0
				}
			]
		},
		{
			"parts": [
				"back"
			],
			"values": [
				{
					"states": [
						"default"
					],
					"slash": 25,
					"impact": 25,
					"shot": 20,
					"fire": 5,
					"water": 5,
					"thunder": 0,
					"ice": 10,
					"dragon": 5,
					"stun": 0
				},
				{
					"states": [
						"broken"
					],
					"slash": 26,
					"impact": 26,
					"shot": 20,
					"fire": 5,
					"water": 10,
					"thunder": 0,
					"ice": 15,
					"dragon": 5,
					"stun": 0
				}
			]
		},
		{
			"parts": [
				"wing"
			],
			"values": [
				{
					"states": [
						"default"
					],
					"slash": 25,
					"impact": 25,
					"shot": 20,
					"fire": 5,
					"water": 5,
					"thunder": 0,
					"ice": 10,
					"dragon": 5,
					"stun": 0
				},
				{
					"states": [
						"broken"
					],
					"slash": 35,
					"impact": 35,
					"shot": 25,
					"fire": 5,
					"water": 10,
					"thunder": 0,
					"ice": 15,
					"dragon": 5,
					"stun": 0
				},
				{
					"states": [
						"charged_electric"
					],
					"slash": 55,
					"impact": 55,
					"shot": 40,
					"fire": 10,
					"water": 12,
					"thunder": 0,
					"ice": 15,
					"dragon": 5,
					"stun": 0
				}
			]
		},
		{
			"parts": [
				"leg"
			],
			"values": [
				{
					"states": [
						"default"
					],
					"slash": 25,
					"impact": 25,
					"shot": 15,
					"fire": 5,
					"water": 5,
					"thunder": 0,
					"ice": 10,
					"dragon": 5,
					"stun": 0
				}
			]
		},
		{
			"parts": [
				"tail"
			],
			"values": [
				{
					"states": [
						"default"
					],
					"slash": 35,
					"impact": 35,
					"shot": 20,
					"fire": 5,
					"water": 10,
					"thunder": 0,
					"ice": 15,
					"dragon": 5,
					"stun": 0
				}
			]
		},
		{
			"parts": [
				"tail_tip"
			],
			"values": [
				{
					"states": [
						"default"
					],
					"slash": 35,
					"impact": 35,
					"shot": 20,
					"fire": 5,
					"water": 10,
					"thunder": 0,
					"ice": 15,
					"dragon": 5,
					"stun": 0
				},
				{
					"states": [
						"broken"
					],
					"slash": 37,
					"impact": 37,
					"shot": 22,
					"fire": 5,
					"water": 10,
					"thunder": 0,
					"ice": 15,
					"dragon": 5,
					"stun": 0
				},
				{
					"states": [
						"charged_electric"
					],
					"slash": 55,
					"impact": 55,
					"shot": 45,
					"fire": 5,
					"water": 15,
					"thunder": 0,
					"ice": 25,
					"dragon": 5,
					"stun": 0
				}
			]
		}
	]
}
